htpio/__init__.py
htpio/__main__.py
htpio/bridge.py
htpio/decorators.py
htpio/exceptions.py
htpio/socketio.py
htpio/telnetio.py
htpio-1.1.0.4.dist-info/METADATA
htpio-1.1.0.4.dist-info/WHEEL
htpio-1.1.0.4.dist-info/entry_points.txt
htpio-1.1.0.4.dist-info/license.txt
htpio-1.1.0.4.dist-info/top_level.txt
htpio-1.1.0.4.dist-info/RECORD
