Metadata-Version: 2.1
Name: htpio
Version: 1.1.0.4
Summary: Remote GPIO access library
Home-page: https://bitbucket.org/hilscherdtc/htpio
Author: Branimir Georgiev
Author-email: bgeorgiev@hilscher.com
License: Copyright (c) Hilscher GmbH
Project-URL: Hilscher, https://www.hilscher.com
Project-URL: Ticket, https://ticket.hilscher.com/browse/PSTSKVARNA-765
Project-URL: Documentation, https://kb.hilscher.com/display/EBG/Power+Reset+Automated+Tests
Keywords: raspberry gpio telnet pigpio
Platform: UNKNOWN
Classifier: Development Status :: 5 - Production/Stable
Classifier: Intended Audience :: Developers
Classifier: License :: Other/Proprietary License
Classifier: Operating System :: OS Independent
Classifier: Programming Language :: Python :: 2
Classifier: Programming Language :: Python :: 2.7
Classifier: Programming Language :: Python :: 3
Classifier: Programming Language :: Python :: 3.4
Classifier: Programming Language :: Python :: 3.5
Classifier: Programming Language :: Python :: 3.6
Classifier: Programming Language :: Python :: 3.7
Requires-Dist: pigpio
